COPYING
README.md
setup.py
./CSVReader.py
./DFReader.py
./__init__.py
./fgFDM.py
./mavexpression.py
./mavextra.py
./mavparm.py
./mavtestgen.py
./mavutil.py
./mavwp.py
./quaternion.py
./rotmat.py
./dialects/__init__.py
./dialects/v10/__init__.py
./dialects/v20/__init__.py
./generator/__init__.py
./generator/mavcrc.py
./generator/mavgen.py
./generator/mavgen_c.py
./generator/mavgen_cpp11.py
./generator/mavgen_cs.py
./generator/mavgen_java.py
./generator/mavgen_javascript.py
./generator/mavgen_javascript_stable.py
./generator/mavgen_lua.py
./generator/mavgen_objc.py
./generator/mavgen_python.py
./generator/mavgen_swift.py
./generator/mavgen_typescript.py
./generator/mavgen_wlua.py
./generator/mavparse.py
./generator/mavschema.xsd
./generator/mavtemplate.py
./generator/C/include_v1.0/checksum.h
./generator/C/include_v1.0/mavlink_conversions.h
./generator/C/include_v1.0/mavlink_helpers.h
./generator/C/include_v1.0/mavlink_types.h
./generator/C/include_v1.0/protocol.h
./generator/C/include_v2.0/checksum.h
./generator/C/include_v2.0/mavlink_conversions.h
./generator/C/include_v2.0/mavlink_get_info.h
./generator/C/include_v2.0/mavlink_helpers.h
./generator/C/include_v2.0/mavlink_sha256.h
./generator/C/include_v2.0/mavlink_types.h
./generator/C/include_v2.0/protocol.h
./generator/CPP11/include_v2.0/message.hpp
./generator/CPP11/include_v2.0/msgmap.hpp
./generator/CS/MAVLink.csproj
./generator/CS/MAVLinkMessage.cs
./generator/CS/MavlinkCRC.cs
./generator/CS/MavlinkParse.cs
./generator/CS/MavlinkUtil.cs
./generator/java/lib/Parser.java
./generator/java/lib/Messages/MAVLinkMessage.java
./generator/java/lib/Messages/MAVLinkPayload.java
./generator/java/lib/Messages/MAVLinkStats.java
./generator/swift/MAVLink.swift
./mavnative/mavlink_defaults.h
./message_definitions/v1.0/ASLUAV.xml
./message_definitions/v1.0/AVSSUAS.xml
./message_definitions/v1.0/all.xml
./message_definitions/v1.0/ardupilotmega.xml
./message_definitions/v1.0/bell.xml
./message_definitions/v1.0/common.xml
bell_avr_pymavlink.egg-info/PKG-INFO
bell_avr_pymavlink.egg-info/SOURCES.txt
bell_avr_pymavlink.egg-info/dependency_links.txt
bell_avr_pymavlink.egg-info/requires.txt
bell_avr_pymavlink.egg-info/top_level.txt
